biothings_mcp/__init__.py
biothings_mcp/biothings_api.py
biothings_mcp/download_api.py
biothings_mcp/server.py
biothings_mcp-0.1.6.dist-info/METADATA
biothings_mcp-0.1.6.dist-info/WHEEL
biothings_mcp-0.1.6.dist-info/entry_points.txt
biothings_mcp-0.1.6.dist-info/licenses/LICENSE
biothings_mcp-0.1.6.dist-info/RECORD
