Metadata-Version: 2.4
Name: biothings-mcp
Version: 0.1.6
Summary: MCP for Biothings
Author-email: antonkulaga <antonkulaga@gmail.com>
License-File: LICENSE
Requires-Python: >=3.10
Requires-Dist: aiosqlite>=0.21.0
Requires-Dist: biopython>=1.85
Requires-Dist: biothings-typed-client>=0.0.7
Requires-Dist: eliot>=1.17.5
Requires-Dist: fastmcp>=2.10.2
Requires-Dist: hishel<0.5
Requires-Dist: huggingface-hub>=0.33.2
Requires-Dist: pycomfort>=0.0.18
Requires-Dist: sqlite-utils>=3.38
Requires-Dist: typer>=0.16.0
